README.md
setup.py
sctr/__init__.py
sctr/app.py
sctr/handlers.py
sctr/services.py
sctr.egg-info/PKG-INFO
sctr.egg-info/SOURCES.txt
sctr.egg-info/dependency_links.txt
sctr.egg-info/requires.txt
sctr.egg-info/top_level.txt